__init__.py
gratheory.py
Gratheory-0.1.1.dist-info/LICENSE
Gratheory-0.1.1.dist-info/METADATA
Gratheory-0.1.1.dist-info/WHEEL
Gratheory-0.1.1.dist-info/top_level.txt
Gratheory-0.1.1.dist-info/RECORD
