Metadata-Version: 2.1
Name: Gratheory
Version: 0.1.1
Summary: Create and use graphs theory for maths
Author-email: Samuel Taylor <sam.w.taylor@hotmail.co.uk>
Project-URL: Homepage, https://github.com/Samuelt797/Gratheory
Project-URL: Bug Tracker, https://github.com/Samuelt797/Gratheory/issues
Classifier: Programming Language :: Python :: 3
Classifier: License :: OSI Approved :: MIT License
Classifier: Operating System :: OS Independent
Requires-Python: >=3.9
License-File: LICENSE
